{
    "id": "0100092021C80000",
    "name": "Tomb Raider Definitive Edition",
    "releaseDate": 20251120,
    "version": 0,
    "description": "<p>The cinematic action-adventure that forced Lara Croft to grow from an inexperienced young woman into a hardened survivor has been re-built for next-gen consoles, featuring an obsessively detailed Lara and a stunningly lifelike world. Lara must endure high-octane combat, customize her weapons and gear, and overcome grueling environments to survive her first adventure and uncover the island\u2019s deadly secret. The Definitive Edition of the critically-acclaimed action-adventure includes bonus content and combines all of the downloadable content.</p>"
}
